odoo/addons/l10n_fr_state/README.rst
odoo/addons/l10n_fr_state/__init__.py
odoo/addons/l10n_fr_state/__manifest__.py
odoo/addons/l10n_fr_state/pre_init_hook.py
odoo/addons/l10n_fr_state/data/res_country_state.xml
odoo/addons/l10n_fr_state/i18n/fr.po
odoo/addons/l10n_fr_state/i18n/l10n_fr_state.pot
odoo/addons/l10n_fr_state/readme/CONTRIBUTORS.md
odoo/addons/l10n_fr_state/readme/DESCRIPTION.md
odoo/addons/l10n_fr_state/static/description/icon.png
odoo/addons/l10n_fr_state/static/description/index.html
odoo/addons/l10n_fr_state/static/src/img/screenshots/1.png
odoo_addon_l10n_fr_state-18.0.1.0.0.3.dist-info/METADATA
odoo_addon_l10n_fr_state-18.0.1.0.0.3.dist-info/WHEEL
odoo_addon_l10n_fr_state-18.0.1.0.0.3.dist-info/top_level.txt
odoo_addon_l10n_fr_state-18.0.1.0.0.3.dist-info/RECORD
