Metadata-Version: 2.1
Name: odoo-addon-l10n_fr_state
Version: 18.0.1.0.0.3
Requires-Python: >=3.10
Requires-Dist: odoo==18.0.*
Summary: =?utf-8?q?Populate_Database_with_French_States_=28R=C3=A9gions=29?=
Home-page: https://github.com/OCA/l10n-france
License: AGPL-3
Author: GRAP, Akretion, Nicolas JEUDY, Odoo Community Association (OCA)
Author-email: support@odoo-community.org
Classifier: Programming Language :: Python
Classifier: Framework :: Odoo
Classifier: Framework :: Odoo :: 18.0
Classifier: License :: OSI Approved :: GNU Affero General Public License v3
